odoo/addons/cooperator_worker/README.rst
odoo/addons/cooperator_worker/__init__.py
odoo/addons/cooperator_worker/__manifest__.py
odoo/addons/cooperator_worker/demo/product_share.xml
odoo/addons/cooperator_worker/i18n/cooperator_worker.pot
odoo/addons/cooperator_worker/i18n/fr.po
odoo/addons/cooperator_worker/models/__init__.py
odoo/addons/cooperator_worker/models/product_template.py
odoo/addons/cooperator_worker/models/res_partner.py
odoo/addons/cooperator_worker/readme/CONTRIBUTORS.rst
odoo/addons/cooperator_worker/readme/DESCRIPTION.rst
odoo/addons/cooperator_worker/static/description/index.html
odoo/addons/cooperator_worker/tests/__init__.py
odoo/addons/cooperator_worker/tests/test_base.py
odoo/addons/cooperator_worker/tests/test_workers.py
odoo/addons/cooperator_worker/views/product_template_views.xml
odoo12_addon_cooperator_worker-12.0.2.0.1.dist-info/METADATA
odoo12_addon_cooperator_worker-12.0.2.0.1.dist-info/WHEEL
odoo12_addon_cooperator_worker-12.0.2.0.1.dist-info/top_level.txt
odoo12_addon_cooperator_worker-12.0.2.0.1.dist-info/RECORD
